versioning/__init__.py
versioning/version.py
versioning/versioning.py
remla24_team7_libversion-0.0.1.dist-info/METADATA
remla24_team7_libversion-0.0.1.dist-info/WHEEL
remla24_team7_libversion-0.0.1.dist-info/top_level.txt
remla24_team7_libversion-0.0.1.dist-info/RECORD
